sci_writer/__init__.py
sci_writer/_compiler.py
sci_writer/_content.py
sci_writer/_jobs.py
sci_writer/_project.py
sci_writer/mcp_server.py
sci_writer/_analysis/__init__.py
sci_writer/_analysis/outline.py
sci_writer/_analysis/validation.py
sci_writer/_analysis/versions.py
sci_writer/_analysis/wordcount.py
sci_writer/_cli/__init__.py
sci_writer/_cli/__main__.py
sci_writer/_cli/analysis_cmds.py
sci_writer/_cli/figure_cmds.py
sci_writer/_cli/info_cmds.py
sci_writer/_cli/jobs.py
sci_writer/_cli/main.py
sci_writer/_cli/mcp.py
sci_writer/_cli/media_cmds.py
sci_writer/_cli/table_cmds.py
sci_writer/_mcp/__init__.py
sci_writer/_mcp/handlers/__init__.py
sci_writer/_mcp/handlers/_utils.py
sci_writer/_mcp/handlers/compile.py
sci_writer/_mcp/handlers/content.py
sci_writer/_mcp/handlers/inspection.py
sci_writer/_mcp/handlers/jobs.py
sci_writer/_mcp/handlers/media_crud.py
sci_writer/_mcp/handlers/project.py
sci_writer/_mcp/handlers/validation.py
sci_writer/_mcp/tool_schemas/__init__.py
sci_writer/_mcp/tool_schemas/compile.py
sci_writer/_mcp/tool_schemas/content.py
sci_writer/_mcp/tool_schemas/inspection.py
sci_writer/_mcp/tool_schemas/jobs.py
sci_writer/_mcp/tool_schemas/media_crud.py
sci_writer/_mcp/tool_schemas/project.py
sci_writer/_mcp/tool_schemas/validation.py
sci_writer/_media/__init__.py
sci_writer/_media/_utils.py
sci_writer/_media/figures.py
sci_writer/_media/references.py
sci_writer/_media/tables.py
sci_writer-0.1.1.dist-info/METADATA
sci_writer-0.1.1.dist-info/WHEEL
sci_writer-0.1.1.dist-info/entry_points.txt
sci_writer-0.1.1.dist-info/licenses/LICENSE
sci_writer-0.1.1.dist-info/RECORD
