Metadata-Version: 2.4
Name: sci-writer
Version: 0.1.1
Summary: LaTeX manuscript compilation system for scientific documents
Project-URL: Homepage, https://github.com/ywatanabe1989/sci-writer
Project-URL: Documentation, https://github.com/ywatanabe1989/sci-writer#readme
Project-URL: Repository, https://github.com/ywatanabe1989/sci-writer.git
Project-URL: Issues, https://github.com/ywatanabe1989/sci-writer/issues
Author-email: Yusuke Watanabe <ywatanabe@scitex.ai>
License-Expression: AGPL-3.0
License-File: LICENSE
Keywords: academic,bibliography,bibtex,compilation,latex,manuscript,paper,scientific-writing
Classifier: Development Status :: 4 - Beta
Classifier: Environment :: Console
Classifier: Intended Audience :: Science/Research
Classifier: License :: OSI Approved :: GNU Affero General Public License v3
Classifier: Operating System :: OS Independent
Classifier: Programming Language :: Python :: 3
Classifier: Programming Language :: Python :: 3.9
Classifier: Programming Language :: Python :: 3.10
Classifier: Programming Language :: Python :: 3.11
Classifier: Programming Language :: Python :: 3.12
Classifier: Topic :: Scientific/Engineering
Classifier: Topic :: Text Processing :: Markup :: LaTeX
Requires-Python: >=3.9
Requires-Dist: bibtexparser>=1.4.0
Requires-Dist: click>=8.0.0
Requires-Dist: rich>=13.0.0
Provides-Extra: all
Requires-Dist: mcp>=1.0.0; extra == 'all'
Requires-Dist: opencv-python>=4.8.0; extra == 'all'
Requires-Dist: pillow>=9.0.0; extra == 'all'
Requires-Dist: pytest-cov>=4.0.0; extra == 'all'
Requires-Dist: pytest>=7.0.0; extra == 'all'
Provides-Extra: dev
Requires-Dist: pre-commit>=3.5.0; extra == 'dev'
Requires-Dist: pytest-cov>=4.0.0; extra == 'dev'
Requires-Dist: pytest-xdist>=3.0.0; extra == 'dev'
Requires-Dist: pytest>=7.0.0; extra == 'dev'
Provides-Extra: imaging
Requires-Dist: opencv-python>=4.8.0; extra == 'imaging'
Requires-Dist: pillow>=9.0.0; extra == 'imaging'
Provides-Extra: mcp
Requires-Dist: mcp>=1.0.0; extra == 'mcp'
